{
  "posts": [
    {
      "format": "",
      "title": "2018/06/08",
      "subtitle": "今日のやつ",
      "date": "2018/06/08",
      "imgsrc": "/img/noimg.jpg",
      "link": "/post/20180608"
    },
    {
      "format": "",
      "title": "2018/06/07",
      "subtitle": "今日のやつ",
      "date": "2018/06/07",
      "imgsrc": "/img/dist/20180607.jpg",
      "link": "/post/20180607"
    },
    {
      "format": "",
      "title": "preact-cli でポートフォリオサイトを作った",
      "subtitle": "あとで書く",
      "date": "2018/06/06",
      "imgsrc": "/img/dist/20180606.png",
      "link": "/post/20180606"
    },
    {
      "format": "",
      "title": "hello, world!",
      "subtitle": "はじめのごあいさつ",
      "date": "2018/06/05",
      "imgsrc": "/img/dist/20180605.jpg",
      "link": "/post/20180605"
    }
  ]
}
